blamscamp/__init__.py
blamscamp-0.3.1.dist-info/LICENSE
blamscamp-0.3.1.dist-info/METADATA
blamscamp-0.3.1.dist-info/WHEEL
blamscamp-0.3.1.dist-info/entry_points.txt
blamscamp-0.3.1.dist-info/RECORD
