Metadata-Version: 2.1
Name: blamscamp
Version: 0.3.1
Summary: Tools for publishing albums to the web and digital stores
License: CC0
Author: fluffy
Author-email: fluffy@beesbuzz.biz
Requires-Python: >=3.8,<4.0
Classifier: License :: Other/Proprietary License
Classifier: Programming Language :: Python :: 3
Classifier: Programming Language :: Python :: 3.8
Classifier: Programming Language :: Python :: 3.9
Classifier: Programming Language :: Python :: 3.10
Classifier: Programming Language :: Python :: 3.11
Requires-Dist: bandcrash (>=0.3.0,<0.4.0)
